git_mcps/__init__.py
git_mcps/__main__.py
git_mcps/py.typed
git_mcps/server.py
git_mcps-0.7.2.dist-info/METADATA
git_mcps-0.7.2.dist-info/WHEEL
git_mcps-0.7.2.dist-info/entry_points.txt
git_mcps-0.7.2.dist-info/licenses/LICENSE
git_mcps-0.7.2.dist-info/RECORD
